python_did_resolver/.mypy_cache/.gitignore
python_did_resolver/.mypy_cache/3.10/@plugins_snapshot.json
python_did_resolver/.mypy_cache/3.10/Crypto/Hash/SHAKE128.data.json
python_did_resolver/.mypy_cache/3.10/Crypto/Hash/SHAKE128.meta.json
python_did_resolver/.mypy_cache/3.10/Crypto/Hash/__init__.data.json
python_did_resolver/.mypy_cache/3.10/Crypto/Hash/__init__.meta.json
python_did_resolver/.mypy_cache/3.10/Crypto/__init__.data.json
python_did_resolver/.mypy_cache/3.10/Crypto/__init__.meta.json
python_did_resolver/.mypy_cache/3.10/_ast.data.json
python_did_resolver/.mypy_cache/3.10/_ast.meta.json
python_did_resolver/.mypy_cache/3.10/_collections_abc.data.json
python_did_resolver/.mypy_cache/3.10/_collections_abc.meta.json
python_did_resolver/.mypy_cache/3.10/_typeshed/__init__.data.json
python_did_resolver/.mypy_cache/3.10/_typeshed/__init__.meta.json
python_did_resolver/.mypy_cache/3.10/abc.data.json
python_did_resolver/.mypy_cache/3.10/abc.meta.json
python_did_resolver/.mypy_cache/3.10/array.data.json
python_did_resolver/.mypy_cache/3.10/array.meta.json
python_did_resolver/.mypy_cache/3.10/builtins.data.json
python_did_resolver/.mypy_cache/3.10/builtins.meta.json
python_did_resolver/.mypy_cache/3.10/codecs.data.json
python_did_resolver/.mypy_cache/3.10/codecs.meta.json
python_did_resolver/.mypy_cache/3.10/collections/__init__.data.json
python_did_resolver/.mypy_cache/3.10/collections/__init__.meta.json
python_did_resolver/.mypy_cache/3.10/collections/abc.data.json
python_did_resolver/.mypy_cache/3.10/collections/abc.meta.json
python_did_resolver/.mypy_cache/3.10/contextlib.data.json
python_did_resolver/.mypy_cache/3.10/contextlib.meta.json
python_did_resolver/.mypy_cache/3.10/ctypes/__init__.data.json
python_did_resolver/.mypy_cache/3.10/ctypes/__init__.meta.json
python_did_resolver/.mypy_cache/3.10/did_resolver/__init__.data.json
python_did_resolver/.mypy_cache/3.10/did_resolver/__init__.meta.json
python_did_resolver/.mypy_cache/3.10/did_resolver/main.data.json
python_did_resolver-0.0.3.dist-info/WHEEL
python_did_resolver-0.0.3.dist-info/METADATA
python_did_resolver-0.0.3.dist-info/RECORD
