Metadata-Version: 2.1
Name: python-did-resolver
Version: 0.0.3
License: MIT
Author-email: tintinthong <justinthong93@gmail.com>
Requires-Python: >=3.9
Requires-Dist: did-resolver>=0.0.2
Requires-Dist: pycryptodome>=3.15.0
Requires-Dist: shortuuid>=1.0.9
Requires-Dist: typing-extensions>=4.3.0
